pypdown-0.1.4.dist-info/METADATA
pypdown-0.1.4.dist-info/WHEEL
pypdown/__init__.py
pypdown/models.py
pypdown/run.py
pypdown-0.1.4.dist-info/RECORD
